{
  "calculation_time": 42.019733527,
  "qmmbe": {
    "b_formation_time": 3.023633987,
    "b_tflops": 4.866590445230367,
    "diag_time": 8.142010481999998,
    "expanded_elec_energy": -5934.718178049432,
    "expanded_hf_energy": -1691.6036240598721,
    "expanded_nuc_repulsion_energy": 4491.561789854783,
    "expanded_xc_energy": -248.44723586522272,
    "homo": -0.17655113570904468,
    "lumo": -0.09752510778223229,
    "method": "RestrictedKSDFT",
    "mp2_tflops": 0.0,
    "mp2_time": 6.95335580497654e-310,
    "n_atoms": 68,
    "nmers": [
      [
        {
          "fragments": [
            0
          ],
          "hf_energy": -1691.6036240598721,
          "num_basis_fns": 1508,
          "num_iters": 17,
          "schema_version": "0.2.0"
        }
      ]
    ],
    "num_iters": 17,
    "ri_fock_time": 4.917152484000001,
    "ri_tflops": 0.1164847032244282,
    "scf_tflops": 0.038139670788006626,
    "scf_time": 41.795082732,
    "schema_version": "0.2.0",
    "tflops": 0.3848965816291283,
    "total_time": 42.015051,
    "transforms_time": 0.7524142180000002,
    "xc_tflops": 0.0,
    "xc_time": 26.396084740000006
  },
  "schema_version": "0.2.0"
}
