{
  "calculation_time": 33.411261197,
  "qmmbe": {
    "b_formation_time": 2.246958715,
    "b_tflops": 6.899490564640838,
    "diag_time": 4.550499472,
    "expanded_elec_energy": -6042.288118179806,
    "expanded_hf_energy": -1691.479812061305,
    "expanded_nuc_repulsion_energy": 4599.053663034109,
    "expanded_xc_energy": -248.24535691560868,
    "homo": -0.1785945553878289,
    "lumo": -0.10456183197805903,
    "method": "RestrictedKSDFT",
    "mp2_tflops": 0.0,
    "mp2_time": 6.95335580498286e-310,
    "n_atoms": 68,
    "nmers": [
      [
        {
          "fragments": [
            0
          ],
          "hf_energy": -1691.479812061305,
          "num_basis_fns": 1508,
          "num_iters": 17,
          "schema_version": "0.2.0"
        }
      ]
    ],
    "num_iters": 17,
    "ri_fock_time": 0.272435827,
    "ri_tflops": 2.102414554338332,
    "scf_tflops": 35.74564072340373,
    "scf_time": 33.200451213,
    "schema_version": "0.2.0",
    "tflops": 33.31334395467704,
    "total_time": 33.406777,
    "transforms_time": 0.09002247999999996,
    "xc_tflops": 44.645145658673634,
    "xc_time": 24.547807451
  },
  "schema_version": "0.2.0"
}
