{
  "calculation_time": 33.648674911,
  "qmmbe": {
    "b_formation_time": 2.256389206,
    "b_tflops": 7.016242098963488,
    "diag_time": 4.5546199750000005,
    "expanded_elec_energy": -6106.069157670063,
    "expanded_hf_energy": -1691.4843175806734,
    "expanded_nuc_repulsion_energy": 4662.83780768189,
    "expanded_xc_energy": -248.2529675925005,
    "homo": -0.16904930200259655,
    "lumo": -0.11637494717298945,
    "method": "RestrictedKSDFT",
    "mp2_tflops": 0.0,
    "mp2_time": 6.953355804956e-310,
    "n_atoms": 68,
    "nmers": [
      [
        {
          "fragments": [
            0
          ],
          "hf_energy": -1691.4843175806734,
          "num_basis_fns": 1508,
          "num_iters": 17,
          "schema_version": "0.2.0"
        }
      ]
    ],
    "num_iters": 17,
    "ri_fock_time": 0.27210162700000007,
    "ri_tflops": 2.1049967768402937,
    "scf_tflops": 35.535420162120495,
    "scf_time": 33.446824793,
    "schema_version": "0.2.0",
    "tflops": 33.1362552672612,
    "total_time": 33.644064,
    "transforms_time": 0.09109711600000002,
    "xc_tflops": 44.27371325061637,
    "xc_time": 24.789930605000006
  },
  "schema_version": "0.2.0"
}
