{
  "calculation_time": 22.671805838,
  "qmmbe": {
    "b_formation_time": 1.623386761,
    "b_tflops": 5.811675299490754,
    "diag_time": 3.527685219,
    "expanded_elec_energy": -4919.834385580957,
    "expanded_hf_energy": -1460.4166951614086,
    "expanded_nuc_repulsion_energy": 3673.556648304067,
    "expanded_xc_energy": -214.13895788451853,
    "homo": -0.17317535931522127,
    "lumo": -0.1103376423642486,
    "method": "RestrictedKSDFT",
    "mp2_tflops": 0.0,
    "mp2_time": 6.95335580498286e-310,
    "n_atoms": 58,
    "nmers": [
      [
        {
          "fragments": [
            0
          ],
          "hf_energy": -1460.4166951614086,
          "num_basis_fns": 1298,
          "num_iters": 17,
          "schema_version": "0.2.0"
        }
      ]
    ],
    "num_iters": 17,
    "ri_fock_time": 0.188177546,
    "ri_tflops": 1.9409252490517652,
    "scf_tflops": 33.65410721228907,
    "scf_time": 22.511275587,
    "schema_version": "0.2.0",
    "tflops": 31.128023795660273,
    "total_time": 22.667809,
    "transforms_time": 0.07875617399999997,
    "xc_tflops": 43.40625752095863,
    "xc_time": 16.017468647999998
  },
  "schema_version": "0.2.0"
}
