{
  "calculation_time": 23.563372522,
  "qmmbe": {
    "b_formation_time": 1.742823864,
    "b_tflops": 6.039773461442573,
    "diag_time": 3.2775172379999993,
    "expanded_elec_energy": -5156.644290107975,
    "expanded_hf_energy": -1537.8457241612914,
    "expanded_nuc_repulsion_energy": 3844.5362612412546,
    "expanded_xc_energy": -225.7376952945706,
    "homo": -0.18155501673520832,
    "lumo": -0.10392219609129248,
    "method": "RestrictedKSDFT",
    "mp2_tflops": 0.0,
    "mp2_time": 6.95335580497496e-310,
    "n_atoms": 62,
    "nmers": [
      [
        {
          "fragments": [
            0
          ],
          "hf_energy": -1537.8457241612914,
          "num_basis_fns": 1372,
          "num_iters": 16,
          "schema_version": "0.2.0"
        }
      ]
    ],
    "num_iters": 16,
    "ri_fock_time": 0.19649745200000002,
    "ri_tflops": 2.0661467972622867,
    "scf_tflops": 36.647119048127195,
    "scf_time": 23.402411694,
    "schema_version": "0.2.0",
    "tflops": 33.78741672692295,
    "total_time": 23.559275,
    "transforms_time": 0.082793162,
    "xc_tflops": 46.28500927716819,
    "xc_time": 16.948253043999998
  },
  "schema_version": "0.2.0"
}
