{
  "calculation_time": 30.169775778,
  "qmmbe": {
    "b_formation_time": 1.932331824,
    "b_tflops": 6.4970264547958925,
    "diag_time": 4.098799974,
    "expanded_elec_energy": -5562.785876378235,
    "expanded_hf_energy": -1614.201152830365,
    "expanded_nuc_repulsion_energy": 4185.588918103095,
    "expanded_xc_energy": -237.00419455522493,
    "homo": -0.16659201281293032,
    "lumo": -0.10244267596996154,
    "method": "RestrictedKSDFT",
    "mp2_tflops": 0.0,
    "mp2_time": 6.95335580496705e-310,
    "n_atoms": 64,
    "nmers": [
      [
        {
          "fragments": [
            0
          ],
          "hf_energy": -1614.201152830365,
          "num_basis_fns": 1434,
          "num_iters": 18,
          "schema_version": "0.2.0"
        }
      ]
    ],
    "num_iters": 18,
    "ri_fock_time": 0.249893612,
    "ri_tflops": 2.086723929157501,
    "scf_tflops": 35.606144151817475,
    "scf_time": 29.991222526,
    "schema_version": "0.2.0",
    "tflops": 33.25115030999571,
    "total_time": 30.165406,
    "transforms_time": 0.09313744200000001,
    "xc_tflops": 44.494434178916606,
    "xc_time": 22.230845273
  },
  "schema_version": "0.2.0"
}
