{
  "calculation_time": 47.095366339,
  "qmmbe": {
    "b_formation_time": 4.795014813,
    "b_tflops": 28.341188936973573,
    "diag_time": 1.9560865589999998,
    "expanded_elec_energy": -5056.4107429523165,
    "expanded_hf_energy": -1453.5627134817348,
    "expanded_mp2_os_correction": -3.59961666785788,
    "expanded_mp2_ss_correction": -0.1151930349283206,
    "expanded_nuc_repulsion_energy": 3669.5533906422897,
    "expanded_xc_energy": -66.705361171708,
    "homo": -0.2059834541749992,
    "lumo": -0.034844127725273344,
    "method": "RestrictedKSDFT",
    "mp2_tflops": 61.5350902566219,
    "mp2_time": 12.055441,
    "n_atoms": 56,
    "nmers": [
      [
        {
          "fragments": [
            0
          ],
          "hf_energy": -1453.5627134817348,
          "mp2_os_correction": -3.59961666785788,
          "mp2_ss_correction": -0.1151930349283206,
          "num_basis_fns": 2706,
          "num_iters": 17,
          "schema_version": "0.2.0"
        }
      ]
    ],
    "num_iters": 17,
    "ri_fock_time": 20.138190586,
    "ri_tflops": 34.28839724031401,
    "scf_tflops": 28.911111006042304,
    "scf_time": 34.484452519,
    "schema_version": "0.2.0",
    "tflops": 36.48730702653026,
    "total_time": 47.088811,
    "transforms_time": 0.11385742700000002,
    "xc_tflops": 23.96309160323771,
    "xc_time": 6.059142175000001
  },
  "schema_version": "0.2.0"
}
