{
  "calculation_time": 72.431683016,
  "qmmbe": {
    "b_formation_time": 6.463029525,
    "b_tflops": 26.367803000221638,
    "diag_time": 2.2140458,
    "expanded_elec_energy": -5397.3759914559105,
    "expanded_hf_energy": -1531.7878305782533,
    "expanded_mp2_os_correction": -3.8257261685930626,
    "expanded_mp2_ss_correction": -0.1204728966097056,
    "expanded_nuc_repulsion_energy": 3936.045133344077,
    "expanded_xc_energy": -70.45697246641978,
    "homo": -0.2182885890623938,
    "lumo": -0.02311443511741351,
    "method": "RestrictedKSDFT",
    "mp2_tflops": 63.22384803646378,
    "mp2_time": 21.775026,
    "n_atoms": 62,
    "nmers": [
      [
        {
          "fragments": [
            0
          ],
          "hf_energy": -1531.7878305782533,
          "mp2_os_correction": -3.8257261685930626,
          "mp2_ss_correction": -0.1204728966097056,
          "num_basis_fns": 2940,
          "num_iters": 16,
          "schema_version": "0.2.0"
        }
      ]
    ],
    "num_iters": 16,
    "ri_fock_time": 27.506332031000003,
    "ri_tflops": 33.545904512729535,
    "scf_tflops": 29.484198412148835,
    "scf_time": 49.9667624,
    "schema_version": "0.2.0",
    "tflops": 38.79924780192855,
    "total_time": 72.424573,
    "transforms_time": 3.1506674770000003,
    "xc_tflops": 35.37164873976539,
    "xc_time": 9.459738486
  },
  "schema_version": "0.2.0"
}
