{
  "calculation_time": 30.826393531,
  "qmmbe": {
    "b_formation_time": 3.053350008,
    "b_tflops": 27.304175096129367,
    "diag_time": 1.375429785,
    "expanded_elec_energy": -3990.5588921186704,
    "expanded_hf_energy": -1225.670858155699,
    "expanded_mp2_os_correction": -3.0590039135088585,
    "expanded_mp2_ss_correction": -0.09647905471459339,
    "expanded_nuc_repulsion_energy": 2821.375079063768,
    "expanded_xc_energy": -56.48704510079698,
    "homo": -0.2251422600547393,
    "lumo": -0.015391617662682044,
    "method": "RestrictedKSDFT",
    "mp2_tflops": 55.91574547841749,
    "mp2_time": 6.74048,
    "n_atoms": 50,
    "nmers": [
      [
        {
          "fragments": [
            0
          ],
          "hf_energy": -1225.670858155699,
          "mp2_os_correction": -3.0590039135088585,
          "mp2_ss_correction": -0.09647905471459339,
          "num_basis_fns": 2364,
          "num_iters": 16,
          "schema_version": "0.2.0"
        }
      ]
    ],
    "num_iters": 16,
    "ri_fock_time": 13.315065545000001,
    "ri_tflops": 29.00891734508994,
    "scf_tflops": 24.463902192234194,
    "scf_time": 23.643864634,
    "schema_version": "0.2.0",
    "tflops": 30.87798597247905,
    "total_time": 30.820481,
    "transforms_time": 0.08547948699999997,
    "xc_tflops": 21.101631619352833,
    "xc_time": 4.8496125779999995
  },
  "schema_version": "0.2.0"
}
