{
  "calculation_time": 95.078368342,
  "qmmbe": {
    "b_formation_time": 8.639918173,
    "b_tflops": 25.263643957135425,
    "diag_time": 2.7304250029999997,
    "expanded_elec_energy": -5971.943612384544,
    "expanded_hf_energy": -1684.8856514501883,
    "expanded_mp2_os_correction": -4.1956827308846485,
    "expanded_mp2_ss_correction": -0.13266105590750915,
    "expanded_nuc_repulsion_energy": 4364.648016417832,
    "expanded_xc_energy": -77.59005548347591,
    "method": "RestrictedKSDFT",
    "mp2_tflops": 65.30645018890044,
    "mp2_time": 32.423853,
    "n_atoms": 68,
    "nmers": [
      [
        {
          "fragments": [
            0
          ],
          "hf_energy": -1684.8856514501883,
          "mp2_os_correction": -4.1956827308846485,
          "mp2_ss_correction": -0.13266105590750915,
          "num_basis_fns": 3228,
          "num_iters": 16,
          "schema_version": "0.2.0"
        }
      ]
    ],
    "num_iters": 16,
    "ri_fock_time": 35.36414685900001,
    "ri_tflops": 37.90080259876165,
    "scf_tflops": 32.49313611981613,
    "scf_time": 61.943217936,
    "schema_version": "0.2.0",
    "tflops": 42.518232802802515,
    "total_time": 95.070568,
    "transforms_time": 3.254254947,
    "xc_tflops": 33.65403916606271,
    "xc_time": 10.660463756
  },
  "schema_version": "0.2.0"
}
