{
  "calculation_time": 26.513081359,
  "qmmbe": {
    "b_formation_time": 1.946798319,
    "b_tflops": 6.049775004879692,
    "diag_time": 3.728127077,
    "expanded_elec_energy": -5409.431235671354,
    "expanded_hf_energy": -1615.5872344474578,
    "expanded_nuc_repulsion_energy": 4032.0901413198426,
    "expanded_xc_energy": -238.24614009594598,
    "homo": -0.17100840078765706,
    "lumo": -0.10371945311865738,
    "method": "RestrictedKSDFT",
    "mp2_tflops": 0.0,
    "mp2_time": 6.95335580499235e-310,
    "n_atoms": 64,
    "nmers": [
      [
        {
          "fragments": [
            0
          ],
          "hf_energy": -1615.5872344474578,
          "num_basis_fns": 1434,
          "num_iters": 16,
          "schema_version": "0.2.0"
        }
      ]
    ],
    "num_iters": 16,
    "ri_fock_time": 0.23019405199999998,
    "ri_tflops": 2.0136015210679727,
    "scf_tflops": 36.65544008104977,
    "scf_time": 26.346779517,
    "schema_version": "0.2.0",
    "tflops": 33.893191449717555,
    "total_time": 26.508932,
    "transforms_time": 0.08050522200000002,
    "xc_tflops": 46.27178901294627,
    "xc_time": 19.137382075
  },
  "schema_version": "0.2.0"
}
