{
  "calculation_time": 32.621217266,
  "qmmbe": {
    "b_formation_time": 2.220197424,
    "b_tflops": 7.332349522949451,
    "diag_time": 4.5351120300000005,
    "expanded_elec_energy": -6164.009380983456,
    "expanded_hf_energy": -1693.004907487176,
    "expanded_nuc_repulsion_energy": 4720.940782245196,
    "expanded_xc_energy": -249.93630874891568,
    "homo": -0.16095860285184577,
    "lumo": -0.10926862426573969,
    "method": "RestrictedKSDFT",
    "mp2_tflops": 0.0,
    "mp2_time": 6.9533558049892e-310,
    "n_atoms": 68,
    "nmers": [
      [
        {
          "fragments": [
            0
          ],
          "hf_energy": -1693.004907487176,
          "num_basis_fns": 1508,
          "num_iters": 17,
          "schema_version": "0.2.0"
        }
      ]
    ],
    "num_iters": 17,
    "ri_fock_time": 0.27150076399999995,
    "ri_tflops": 2.1096553813307137,
    "scf_tflops": 36.58013887647945,
    "scf_time": 32.413728417,
    "schema_version": "0.2.0",
    "tflops": 34.08300295240706,
    "total_time": 32.616814,
    "transforms_time": 0.08953823100000002,
    "xc_tflops": 45.89171547096405,
    "xc_time": 23.837217767
  },
  "schema_version": "0.2.0"
}
