{
  "calculation_time": 18.559508632,
  "qmmbe": {
    "b_formation_time": 1.409266644,
    "b_tflops": 5.239197791500414,
    "diag_time": 2.5573839869999997,
    "expanded_elec_energy": -4433.050692289832,
    "expanded_hf_energy": -1385.4612998240045,
    "expanded_nuc_repulsion_energy": 3252.2134014256776,
    "expanded_xc_energy": -204.62400895985,
    "homo": -0.17730712135839194,
    "lumo": -0.09779704952295547,
    "method": "RestrictedKSDFT",
    "mp2_tflops": 0.0,
    "mp2_time": 6.9533558049544e-310,
    "n_atoms": 56,
    "nmers": [
      [
        {
          "fragments": [
            0
          ],
          "hf_energy": -1385.4612998240045,
          "num_basis_fns": 1236,
          "num_iters": 16,
          "schema_version": "0.2.0"
        }
      ]
    ],
    "num_iters": 16,
    "ri_fock_time": 0.14077493,
    "ri_tflops": 2.10859592389071,
    "scf_tflops": 34.29104503567085,
    "scf_time": 18.406183487,
    "schema_version": "0.2.0",
    "tflops": 31.460257470255033,
    "total_time": 18.555625,
    "transforms_time": 0.07529443600000002,
    "xc_tflops": 43.39718230701875,
    "xc_time": 13.264149639000001
  },
  "schema_version": "0.2.0"
}
