{
  "calculation_time": 18.643135588,
  "qmmbe": {
    "b_formation_time": 1.486985832,
    "b_tflops": 5.460028716851957,
    "diag_time": 2.643406618,
    "expanded_elec_energy": -4599.359702257478,
    "expanded_hf_energy": -1385.4313321536952,
    "expanded_nuc_repulsion_energy": 3418.556421704289,
    "expanded_xc_energy": -204.62805160050635,
    "homo": -0.18445771459143764,
    "lumo": -0.08827461261537882,
    "method": "RestrictedKSDFT",
    "mp2_tflops": 0.0,
    "mp2_time": 6.9533558049544e-310,
    "n_atoms": 56,
    "nmers": [
      [
        {
          "fragments": [
            0
          ],
          "hf_energy": -1385.4313321536952,
          "num_basis_fns": 1236,
          "num_iters": 16,
          "schema_version": "0.2.0"
        }
      ]
    ],
    "num_iters": 16,
    "ri_fock_time": 0.14106452200000003,
    "ri_tflops": 2.1042671777103523,
    "scf_tflops": 34.16355594455861,
    "scf_time": 18.494570638,
    "schema_version": "0.2.0",
    "tflops": 31.224014012684272,
    "total_time": 18.639328,
    "transforms_time": 0.070048453,
    "xc_tflops": 43.46215732309145,
    "xc_time": 13.187097386
  },
  "schema_version": "0.2.0"
}
