{
  "calculation_time": 60.636669537,
  "qmmbe": {
    "b_formation_time": 5.556314925,
    "b_tflops": 28.030484809646385,
    "diag_time": 2.20240525,
    "expanded_elec_energy": -5158.147709924151,
    "expanded_hf_energy": -1531.7924914107114,
    "expanded_mp2_os_correction": -3.8232567645831748,
    "expanded_mp2_ss_correction": -0.12029941422115323,
    "expanded_nuc_repulsion_energy": 3696.8125566644394,
    "expanded_xc_energy": -70.45733815099976,
    "homo": -0.2153123986827934,
    "lumo": -0.029518102579502273,
    "method": "RestrictedKSDFT",
    "mp2_tflops": 59.51198293274405,
    "mp2_time": 17.688208,
    "n_atoms": 62,
    "nmers": [
      [
        {
          "fragments": [
            0
          ],
          "hf_energy": -1531.7924914107114,
          "mp2_os_correction": -3.8232567645831748,
          "mp2_ss_correction": -0.12029941422115323,
          "num_basis_fns": 2940,
          "num_iters": 16,
          "schema_version": "0.2.0"
        }
      ]
    ],
    "num_iters": 16,
    "ri_fock_time": 26.493177358,
    "ri_tflops": 34.828767655531124,
    "scf_tflops": 29.52338489824345,
    "scf_time": 42.377632194,
    "schema_version": "0.2.0",
    "tflops": 37.54097038592231,
    "total_time": 60.62937,
    "transforms_time": 0.12400132400000002,
    "xc_tflops": 20.92773027532398,
    "xc_time": 6.674347407
  },
  "schema_version": "0.2.0"
}
