{
  "calculation_time": 34.206526096,
  "qmmbe": {
    "b_formation_time": 2.254121981,
    "b_tflops": 5.095025189765895,
    "diag_time": 5.978335163000001,
    "expanded_elec_energy": -5349.150097637752,
    "expanded_hf_energy": -1536.9233372159367,
    "expanded_nuc_repulsion_energy": 4037.580652657491,
    "expanded_xc_energy": -225.35389223567591,
    "homo": -0.17247712852204466,
    "lumo": -0.10822141173306601,
    "method": "RestrictedKSDFT",
    "mp2_tflops": 0.0,
    "mp2_time": 6.9533558049623e-310,
    "n_atoms": 60,
    "nmers": [
      [
        {
          "fragments": [
            0
          ],
          "hf_energy": -1536.9233372159367,
          "num_basis_fns": 1360,
          "num_iters": 17,
          "schema_version": "0.2.0"
        }
      ]
    ],
    "num_iters": 17,
    "ri_fock_time": 3.815114281,
    "ri_tflops": 0.11010971652725701,
    "scf_tflops": 0.034261707533358186,
    "scf_time": 33.981631836,
    "schema_version": "0.2.0",
    "tflops": 0.367077871270863,
    "total_time": 34.202455,
    "transforms_time": 0.09706301599999999,
    "xc_tflops": 0.0,
    "xc_time": 22.31467968400001
  },
  "schema_version": "0.2.0"
}
