{
  "calculation_time": 26.454067127,
  "qmmbe": {
    "b_formation_time": 1.75937085,
    "b_tflops": 5.728393135282422,
    "diag_time": 3.5741200650000002,
    "expanded_elec_energy": -5058.043188207636,
    "expanded_hf_energy": -1538.018901403267,
    "expanded_nuc_repulsion_energy": 3746.0209602525024,
    "expanded_xc_energy": -225.99667344813298,
    "homo": -0.17184891959394086,
    "lumo": -0.10096313463655669,
    "method": "RestrictedKSDFT",
    "mp2_tflops": 0.0,
    "mp2_time": 6.9533558049781e-310,
    "n_atoms": 62,
    "nmers": [
      [
        {
          "fragments": [
            0
          ],
          "hf_energy": -1538.018901403267,
          "num_basis_fns": 1372,
          "num_iters": 17,
          "schema_version": "0.2.0"
        }
      ]
    ],
    "num_iters": 17,
    "ri_fock_time": 0.209080034,
    "ri_tflops": 2.0631674349163345,
    "scf_tflops": 34.21057734341648,
    "scf_time": 26.297619265,
    "schema_version": "0.2.0",
    "tflops": 31.86602095005058,
    "total_time": 26.450052,
    "transforms_time": 0.08431163000000004,
    "xc_tflops": 42.700254033500855,
    "xc_time": 19.477408375
  },
  "schema_version": "0.2.0"
}
