{
  "calculation_time": 42.332375368,
  "qmmbe": {
    "b_formation_time": 3.024210381,
    "b_tflops": 5.292928443631316,
    "diag_time": 7.879929441999999,
    "expanded_elec_energy": -6120.250622166885,
    "expanded_hf_energy": -1676.5126173624642,
    "expanded_nuc_repulsion_energy": 4675.9343159658865,
    "expanded_xc_energy": -232.1963111614662,
    "homo": -0.16873054916384467,
    "lumo": -0.12430996650622977,
    "method": "RestrictedKSDFT",
    "mp2_tflops": 0.0,
    "mp2_time": 6.95335580496547e-310,
    "n_atoms": 68,
    "nmers": [
      [
        {
          "fragments": [
            0
          ],
          "hf_energy": -1676.5126173624642,
          "num_basis_fns": 1508,
          "num_iters": 18,
          "schema_version": "0.2.0"
        }
      ]
    ],
    "num_iters": 18,
    "ri_fock_time": 5.3874045630000005,
    "ri_tflops": 0.11257101131723564,
    "scf_tflops": 0.04010905640979501,
    "scf_time": 42.097097355,
    "schema_version": "0.2.0",
    "tflops": 0.4146077001550023,
    "total_time": 42.327766,
    "transforms_time": 0.386863363,
    "xc_tflops": 0.0,
    "xc_time": 27.174768417000003
  },
  "schema_version": "0.2.0"
}
