{
  "calculation_time": 38.644202223,
  "qmmbe": {
    "b_formation_time": 2.403271129,
    "b_tflops": 4.848922166765646,
    "diag_time": 7.600482911,
    "expanded_elec_energy": -5353.729858586506,
    "expanded_hf_energy": -1524.2336412743464,
    "expanded_nuc_repulsion_energy": 4040.6505996949168,
    "expanded_xc_energy": -211.1543823827567,
    "homo": -0.18837364401974682,
    "lumo": -0.10395672624881515,
    "method": "RestrictedKSDFT",
    "mp2_tflops": 0.0,
    "mp2_time": 6.9533558049955e-310,
    "n_atoms": 62,
    "nmers": [
      [
        {
          "fragments": [
            0
          ],
          "hf_energy": -1524.2336412743464,
          "num_basis_fns": 1372,
          "num_iters": 18,
          "schema_version": "0.2.0"
        }
      ]
    ],
    "num_iters": 18,
    "ri_fock_time": 4.006724074,
    "ri_tflops": 0.11399378777386705,
    "scf_tflops": 0.032812427301802595,
    "scf_time": 38.458068254,
    "schema_version": "0.2.0",
    "tflops": 0.33168482885437156,
    "total_time": 38.639941,
    "transforms_time": 0.13281012900000003,
    "xc_tflops": 0.0,
    "xc_time": 24.783910488
  },
  "schema_version": "0.2.0"
}
