{
  "calculation_time": 33.092766592,
  "qmmbe": {
    "b_formation_time": 2.619679615,
    "b_tflops": 5.809996227869262,
    "diag_time": 7.207837402,
    "expanded_elec_energy": -5994.140989792891,
    "expanded_hf_energy": -1676.5307931513223,
    "expanded_nuc_repulsion_energy": 4549.795190926444,
    "expanded_xc_energy": -232.18499428487556,
    "homo": -0.1788389925075643,
    "lumo": -0.11790456736872293,
    "method": "RestrictedKSDFT",
    "mp2_tflops": 0.0,
    "mp2_time": 6.953355804956e-310,
    "n_atoms": 68,
    "nmers": [
      [
        {
          "fragments": [
            0
          ],
          "hf_energy": -1676.5307931513223,
          "num_basis_fns": 1508,
          "num_iters": 18,
          "schema_version": "0.2.0"
        }
      ]
    ],
    "num_iters": 18,
    "ri_fock_time": 4.206612022,
    "ri_tflops": 0.1441696017746036,
    "scf_tflops": 0.051937908489423604,
    "scf_time": 32.85492224,
    "schema_version": "0.2.0",
    "tflops": 0.5066152353138298,
    "total_time": 33.087867,
    "transforms_time": 0.18601356599999996,
    "xc_tflops": 0.0,
    "xc_time": 19.518835229
  },
  "schema_version": "0.2.0"
}
