{
  "calculation_time": 28.503888513,
  "qmmbe": {
    "b_formation_time": 2.221726519,
    "b_tflops": 4.897698282889335,
    "diag_time": 5.685501826000001,
    "expanded_elec_energy": -5213.842367074265,
    "expanded_hf_energy": -1524.2305226901967,
    "expanded_nuc_repulsion_energy": 3900.7455917665616,
    "expanded_xc_energy": -211.13374738249342,
    "homo": -0.1844719932937063,
    "lumo": -0.111772661688021,
    "method": "RestrictedKSDFT",
    "mp2_tflops": 0.0,
    "mp2_time": 6.9533558049971e-310,
    "n_atoms": 62,
    "nmers": [
      [
        {
          "fragments": [
            0
          ],
          "hf_energy": -1524.2305226901967,
          "num_basis_fns": 1372,
          "num_iters": 17,
          "schema_version": "0.2.0"
        }
      ]
    ],
    "num_iters": 17,
    "ri_fock_time": 2.828643466,
    "ri_tflops": 0.15249964254066933,
    "scf_tflops": 0.04297050361568254,
    "scf_time": 28.291239182,
    "schema_version": "0.2.0",
    "tflops": 0.4203493249746577,
    "total_time": 28.499813,
    "transforms_time": 0.21980293200000003,
    "xc_tflops": 0.0,
    "xc_time": 17.467714282
  },
  "schema_version": "0.2.0"
}
