{
  "calculation_time": 19.823232729,
  "qmmbe": {
    "b_formation_time": 1.44400217,
    "b_tflops": 5.069456817971402,
    "diag_time": 2.554291502,
    "expanded_elec_energy": -4427.145057092259,
    "expanded_hf_energy": -1384.1958728646284,
    "expanded_nuc_repulsion_energy": 3246.5543812937176,
    "expanded_xc_energy": -203.60519706608713,
    "homo": -0.17968359833543207,
    "lumo": -0.11321011529974027,
    "method": "RestrictedKSDFT",
    "mp2_tflops": 0.0,
    "mp2_time": 6.95335580496863e-310,
    "n_atoms": 56,
    "nmers": [
      [
        {
          "fragments": [
            0
          ],
          "hf_energy": -1384.1958728646284,
          "num_basis_fns": 1236,
          "num_iters": 16,
          "schema_version": "0.2.0"
        }
      ]
    ],
    "num_iters": 16,
    "ri_fock_time": 0.14717648400000002,
    "ri_tflops": 2.0168809276895074,
    "scf_tflops": 31.91003073329098,
    "scf_time": 19.685827633,
    "schema_version": "0.2.0",
    "tflops": 29.448242860091167,
    "total_time": 19.819637,
    "transforms_time": 0.071293654,
    "xc_tflops": 39.577527318177005,
    "xc_time": 14.543259964
  },
  "schema_version": "0.2.0"
}
