{
  "calculation_time": 35.559756258,
  "qmmbe": {
    "b_formation_time": 4.155840703,
    "b_tflops": 3.3592640090719086,
    "diag_time": 4.519373374,
    "expanded_elec_energy": -5796.903384069381,
    "expanded_hf_energy": -1692.1510021173774,
    "expanded_nuc_repulsion_energy": 4353.8171446506685,
    "expanded_xc_energy": -249.06476269866485,
    "homo": -0.17201309021551403,
    "lumo": -0.09862284847567399,
    "method": "RestrictedKSDFT",
    "mp2_tflops": 0.0,
    "mp2_time": 6.9533558049544e-310,
    "n_atoms": 68,
    "nmers": [
      [
        {
          "fragments": [
            0
          ],
          "hf_energy": -1692.1510021173774,
          "num_basis_fns": 1508,
          "num_iters": 15,
          "schema_version": "0.2.0"
        }
      ]
    ],
    "num_iters": 15,
    "ri_fock_time": 0.2785258890000001,
    "ri_tflops": 1.8145099013040036,
    "scf_tflops": 33.480590155171114,
    "scf_time": 33.666169949,
    "schema_version": "0.2.0",
    "tflops": 28.75605523712022,
    "total_time": 34.003591,
    "transforms_time": 0.26464258499999993,
    "xc_tflops": 42.279702007177406,
    "xc_time": 23.13781425
  },
  "schema_version": "0.2.0"
}
