{
  "calculation_time": 21.499194713,
  "qmmbe": {
    "b_formation_time": 1.505977112,
    "b_tflops": 5.856575416606995,
    "diag_time": 2.6784383810000003,
    "expanded_elec_energy": -4734.895402502183,
    "expanded_hf_energy": -1384.677761951989,
    "expanded_nuc_repulsion_energy": 3554.1295943652453,
    "expanded_xc_energy": -203.91195381505133,
    "homo": -0.17158448017860958,
    "lumo": -0.09610888606932151,
    "method": "RestrictedKSDFT",
    "mp2_tflops": 0.0,
    "mp2_time": 6.9533558049813e-310,
    "n_atoms": 56,
    "nmers": [
      [
        {
          "fragments": [
            0
          ],
          "hf_energy": -1384.677761951989,
          "num_basis_fns": 1236,
          "num_iters": 17,
          "schema_version": "0.2.0"
        }
      ]
    ],
    "num_iters": 17,
    "ri_fock_time": 0.149917825,
    "ri_tflops": 2.103751063677718,
    "scf_tflops": 30.84588124794888,
    "scf_time": 21.339157531,
    "schema_version": "0.2.0",
    "tflops": 28.54629958761043,
    "total_time": 21.49553,
    "transforms_time": 0.08132074900000003,
    "xc_tflops": 38.037369763980266,
    "xc_time": 15.878893341000001
  },
  "schema_version": "0.2.0"
}
