{
  "calculation_time": 23.975800993,
  "qmmbe": {
    "b_formation_time": 1.80193645,
    "b_tflops": 6.233547291612865,
    "diag_time": 3.333361313,
    "expanded_elec_energy": -5273.518175634721,
    "expanded_hf_energy": -1537.2687987628071,
    "expanded_nuc_repulsion_energy": 3961.4095625739496,
    "expanded_xc_energy": -225.16018570203573,
    "homo": -0.17055073416431382,
    "lumo": -0.10938333514549103,
    "method": "RestrictedKSDFT",
    "mp2_tflops": 0.0,
    "mp2_time": 6.9533558049623e-310,
    "n_atoms": 62,
    "nmers": [
      [
        {
          "fragments": [
            0
          ],
          "hf_energy": -1537.2687987628071,
          "num_basis_fns": 1372,
          "num_iters": 16,
          "schema_version": "0.2.0"
        }
      ]
    ],
    "num_iters": 16,
    "ri_fock_time": 0.196499765,
    "ri_tflops": 2.066122476635023,
    "scf_tflops": 35.97817804348572,
    "scf_time": 23.803301421,
    "schema_version": "0.2.0",
    "tflops": 33.136557462917395,
    "total_time": 23.971541,
    "transforms_time": 0.081516803,
    "xc_tflops": 45.52010336359507,
    "xc_time": 17.180725891999998
  },
  "schema_version": "0.2.0"
}
