{
  "calculation_time": 36.068399596,
  "qmmbe": {
    "b_formation_time": 2.422806879,
    "b_tflops": 3.773751618577933,
    "diag_time": 5.934263359000001,
    "expanded_elec_energy": -4859.210786011914,
    "expanded_hf_energy": -1460.2807975573833,
    "expanded_nuc_repulsion_energy": 3613.01242406985,
    "expanded_xc_energy": -214.0824356153194,
    "homo": -0.15889121504238143,
    "lumo": -0.11205106198022773,
    "method": "RestrictedKSDFT",
    "mp2_tflops": 0.0,
    "mp2_time": 6.95335580495124e-310,
    "n_atoms": 58,
    "nmers": [
      [
        {
          "fragments": [
            0
          ],
          "hf_energy": -1460.2807975573833,
          "num_basis_fns": 1298,
          "num_iters": 18,
          "schema_version": "0.2.0"
        }
      ]
    ],
    "num_iters": 18,
    "ri_fock_time": 3.6792954060000005,
    "ri_tflops": 0.10510794276353899,
    "scf_tflops": 0.02989784807822594,
    "scf_time": 35.870896753,
    "schema_version": "0.2.0",
    "tflops": 0.28085809204851003,
    "total_time": 36.064316,
    "transforms_time": 0.09392060299999998,
    "xc_tflops": 0.0,
    "xc_time": 24.400258170999997
  },
  "schema_version": "0.2.0"
}
