{
  "calculation_time": 23.965607639,
  "qmmbe": {
    "b_formation_time": 1.755303088,
    "b_tflops": 6.122171869930647,
    "diag_time": 3.2588497320000003,
    "expanded_elec_energy": -5192.849967418077,
    "expanded_hf_energy": -1536.9175269468744,
    "expanded_nuc_repulsion_energy": 3880.4537457793294,
    "expanded_xc_energy": -224.5213053081272,
    "homo": -0.17495476713818336,
    "lumo": -0.09200377698638357,
    "method": "RestrictedKSDFT",
    "mp2_tflops": 0.0,
    "mp2_time": 6.95335580497496e-310,
    "n_atoms": 62,
    "nmers": [
      [
        {
          "fragments": [
            0
          ],
          "hf_energy": -1536.9175269468744,
          "num_basis_fns": 1372,
          "num_iters": 16,
          "schema_version": "0.2.0"
        }
      ]
    ],
    "num_iters": 16,
    "ri_fock_time": 0.20384869099999997,
    "ri_tflops": 1.9916369299619394,
    "scf_tflops": 35.99900443259262,
    "scf_time": 23.786569167,
    "schema_version": "0.2.0",
    "tflops": 33.21619293028579,
    "total_time": 23.961433,
    "transforms_time": 0.08379340000000002,
    "xc_tflops": 45.19131097165455,
    "xc_time": 17.351195409000002
  },
  "schema_version": "0.2.0"
}
