{
  "calculation_time": 28.694041188,
  "qmmbe": {
    "b_formation_time": 2.021254596,
    "b_tflops": 6.322829676787535,
    "diag_time": 3.8539817539999994,
    "expanded_elec_energy": -5594.323598885932,
    "expanded_hf_energy": -1613.1195282716726,
    "expanded_nuc_repulsion_energy": 4216.56870805683,
    "expanded_xc_energy": -235.3646374425699,
    "homo": -0.17518473265548404,
    "lumo": -0.0921187233685511,
    "method": "RestrictedKSDFT",
    "mp2_tflops": 0.0,
    "mp2_time": 6.95335580495757e-310,
    "n_atoms": 64,
    "nmers": [
      [
        {
          "fragments": [
            0
          ],
          "hf_energy": -1613.1195282716726,
          "num_basis_fns": 1434,
          "num_iters": 17,
          "schema_version": "0.2.0"
        }
      ]
    ],
    "num_iters": 17,
    "ri_fock_time": 0.236941252,
    "ri_tflops": 2.078528041946871,
    "scf_tflops": 35.66194256467295,
    "scf_time": 28.515749172,
    "schema_version": "0.2.0",
    "tflops": 33.05965452069822,
    "total_time": 28.689302,
    "transforms_time": 0.085558582,
    "xc_tflops": 44.558164579227856,
    "xc_time": 20.971146565999998
  },
  "schema_version": "0.2.0"
}
