{
  "calculation_time": 34.956676097,
  "qmmbe": {
    "b_formation_time": 2.786585989,
    "b_tflops": 5.073873179825278,
    "diag_time": 7.221554607,
    "expanded_elec_energy": -5832.923368237698,
    "expanded_hf_energy": -1690.3957732822548,
    "expanded_nuc_repulsion_energy": 4389.772481619353,
    "expanded_xc_energy": -247.24488666391,
    "homo": -0.16690893717835145,
    "lumo": -0.1033616836704982,
    "method": "RestrictedKSDFT",
    "mp2_tflops": 0.0,
    "mp2_time": 6.95335580497496e-310,
    "n_atoms": 68,
    "nmers": [
      [
        {
          "fragments": [
            0
          ],
          "hf_energy": -1690.3957732822548,
          "num_basis_fns": 1508,
          "num_iters": 17,
          "schema_version": "0.2.0"
        }
      ]
    ],
    "num_iters": 17,
    "ri_fock_time": 3.150781953,
    "ri_tflops": 0.181787586812422,
    "scf_tflops": 0.04621728803106068,
    "scf_time": 34.738734164,
    "schema_version": "0.2.0",
    "tflops": 0.4461947943134739,
    "total_time": 34.952099,
    "transforms_time": 0.8727695929999998,
    "xc_tflops": 0.0,
    "xc_time": 21.198957979
  },
  "schema_version": "0.2.0"
}
