{
  "calculation_time": 41.580347316,
  "qmmbe": {
    "b_formation_time": 2.675846489,
    "b_tflops": 5.2576751362241545,
    "diag_time": 8.168398033999999,
    "expanded_elec_energy": -5815.294720745356,
    "expanded_hf_energy": -1690.3867023075202,
    "expanded_nuc_repulsion_energy": 4372.151101473439,
    "expanded_xc_energy": -247.24308303560275,
    "homo": -0.16792979782698417,
    "lumo": -0.1002189002904267,
    "method": "RestrictedKSDFT",
    "mp2_tflops": 0.0,
    "mp2_time": 6.9533558049702e-310,
    "n_atoms": 68,
    "nmers": [
      [
        {
          "fragments": [
            0
          ],
          "hf_energy": -1690.3867023075202,
          "num_basis_fns": 1508,
          "num_iters": 18,
          "schema_version": "0.2.0"
        }
      ]
    ],
    "num_iters": 18,
    "ri_fock_time": 4.137401012,
    "ri_tflops": 0.14658129059112823,
    "scf_tflops": 0.04048732663332183,
    "scf_time": 41.363478831,
    "schema_version": "0.2.0",
    "tflops": 0.37548959872998694,
    "total_time": 41.57564,
    "transforms_time": 0.9232565810000004,
    "xc_tflops": 0.0,
    "xc_time": 26.635331751999995
  },
  "schema_version": "0.2.0"
}
