{
  "calculation_time": 31.995173386,
  "qmmbe": {
    "b_formation_time": 2.181665497,
    "b_tflops": 5.298365972167181,
    "diag_time": 5.055158058,
    "expanded_elec_energy": -5335.494892263518,
    "expanded_hf_energy": -1536.1401607991406,
    "expanded_nuc_repulsion_energy": 4023.375554156058,
    "expanded_xc_energy": -224.02082269168102,
    "homo": -0.1751723353828285,
    "lumo": -0.10313284915980132,
    "method": "RestrictedKSDFT",
    "mp2_tflops": 0.0,
    "mp2_time": 6.9533558049955e-310,
    "n_atoms": 62,
    "nmers": [
      [
        {
          "fragments": [
            0
          ],
          "hf_energy": -1536.1401607991406,
          "num_basis_fns": 1372,
          "num_iters": 17,
          "schema_version": "0.2.0"
        }
      ]
    ],
    "num_iters": 17,
    "ri_fock_time": 4.183111577999999,
    "ri_tflops": 0.10312111197527327,
    "scf_tflops": 0.03770475138637219,
    "scf_time": 31.785797503,
    "schema_version": "0.2.0",
    "tflops": 0.3956692470262348,
    "total_time": 31.990843,
    "transforms_time": 0.12944243899999996,
    "xc_tflops": 0.0,
    "xc_time": 21.383381871999998
  },
  "schema_version": "0.2.0"
}
