{
  "calculation_time": 38.67214798,
  "qmmbe": {
    "b_formation_time": 2.518325334,
    "b_tflops": 4.885811820167315,
    "diag_time": 8.589483374999999,
    "expanded_elec_energy": -5505.0463715592705,
    "expanded_hf_energy": -1612.3589006398247,
    "expanded_nuc_repulsion_energy": 4127.528693689735,
    "expanded_xc_energy": -234.84122277028877,
    "homo": -0.16702669278360083,
    "lumo": -0.11102960297339859,
    "method": "RestrictedKSDFT",
    "mp2_tflops": 0.0,
    "mp2_time": 6.95335580498286e-310,
    "n_atoms": 64,
    "nmers": [
      [
        {
          "fragments": [
            0
          ],
          "hf_energy": -1612.3589006398247,
          "num_basis_fns": 1434,
          "num_iters": 18,
          "schema_version": "0.2.0"
        }
      ]
    ],
    "num_iters": 18,
    "ri_fock_time": 4.461657995,
    "ri_tflops": 0.1168756055458258,
    "scf_tflops": 0.03739328350420955,
    "scf_time": 38.469407433,
    "schema_version": "0.2.0",
    "tflops": 0.35252323689611825,
    "total_time": 38.667903,
    "transforms_time": 0.551652485,
    "xc_tflops": 0.0,
    "xc_time": 23.501864496000003
  },
  "schema_version": "0.2.0"
}
