{
  "calculation_time": 43.552941866,
  "qmmbe": {
    "b_formation_time": 3.087011569,
    "b_tflops": 5.274607943789017,
    "diag_time": 9.706662379,
    "expanded_elec_energy": -6168.731051676712,
    "expanded_hf_energy": -1691.4583779544203,
    "expanded_nuc_repulsion_energy": 4725.59329397224,
    "expanded_xc_energy": -248.32062024994804,
    "homo": -0.1844217969949985,
    "lumo": -0.09783482157571863,
    "method": "RestrictedKSDFT",
    "mp2_tflops": 0.0,
    "mp2_time": 6.95335580502397e-310,
    "n_atoms": 68,
    "nmers": [
      [
        {
          "fragments": [
            0
          ],
          "hf_energy": -1691.4583779544203,
          "num_basis_fns": 1508,
          "num_iters": 17,
          "schema_version": "0.2.0"
        }
      ]
    ],
    "num_iters": 17,
    "ri_fock_time": 4.141760652,
    "ri_tflops": 0.13829216507994388,
    "scf_tflops": 0.03684410378164814,
    "scf_time": 43.325826612,
    "schema_version": "0.2.0",
    "tflops": 0.40734932746071806,
    "total_time": 43.548461,
    "transforms_time": 0.094921033,
    "xc_tflops": 0.0,
    "xc_time": 26.30646394
  },
  "schema_version": "0.2.0"
}
