{
  "calculation_time": 42.374589984,
  "qmmbe": {
    "b_formation_time": 2.897568376,
    "b_tflops": 4.715855258250513,
    "diag_time": 6.806358157000001,
    "expanded_elec_energy": -5737.187194592862,
    "expanded_hf_energy": -1614.0448771587207,
    "expanded_nuc_repulsion_energy": 4359.846370605693,
    "expanded_xc_energy": -236.70405317155104,
    "homo": -0.178768030702555,
    "lumo": -0.10375373874039753,
    "method": "RestrictedKSDFT",
    "mp2_tflops": 0.0,
    "mp2_time": 6.95335580501764e-310,
    "n_atoms": 64,
    "nmers": [
      [
        {
          "fragments": [
            0
          ],
          "hf_energy": -1614.0448771587207,
          "num_basis_fns": 1434,
          "num_iters": 17,
          "schema_version": "0.2.0"
        }
      ]
    ],
    "num_iters": 17,
    "ri_fock_time": 4.899905828,
    "ri_tflops": 0.10050989832533574,
    "scf_tflops": 0.03256642067047031,
    "scf_time": 42.150475731,
    "schema_version": "0.2.0",
    "tflops": 0.3520851911409273,
    "total_time": 42.370438,
    "transforms_time": 0.37344354099999993,
    "xc_tflops": 0.0,
    "xc_time": 28.352542325
  },
  "schema_version": "0.2.0"
}
