{
  "calculation_time": 33.195426522,
  "qmmbe": {
    "b_formation_time": 2.312945051,
    "b_tflops": 4.57896947961519,
    "diag_time": 5.646584099,
    "expanded_elec_energy": -5154.36371496161,
    "expanded_hf_energy": -1537.4746279947374,
    "expanded_nuc_repulsion_energy": 3842.471170919929,
    "expanded_xc_energy": -225.58208395305684,
    "homo": -0.16400652498989512,
    "lumo": -0.0974589940471259,
    "method": "RestrictedKSDFT",
    "mp2_tflops": 0.0,
    "mp2_time": 6.9533558049734e-310,
    "n_atoms": 62,
    "nmers": [
      [
        {
          "fragments": [
            0
          ],
          "hf_energy": -1537.4746279947374,
          "num_basis_fns": 1372,
          "num_iters": 17,
          "schema_version": "0.2.0"
        }
      ]
    ],
    "num_iters": 17,
    "ri_fock_time": 3.97299127,
    "ri_tflops": 0.10857489687864327,
    "scf_tflops": 0.03652913884137599,
    "scf_time": 32.988010288,
    "schema_version": "0.2.0",
    "tflops": 0.35218235380444335,
    "total_time": 33.191432,
    "transforms_time": 0.2594059690000001,
    "xc_tflops": 0.0,
    "xc_time": 21.130356206
  },
  "schema_version": "0.2.0"
}
