{
  "calculation_time": 36.153551806,
  "qmmbe": {
    "b_formation_time": 2.916459324,
    "b_tflops": 5.099593128984096,
    "diag_time": 7.529315188000001,
    "expanded_elec_energy": -5951.145066896647,
    "expanded_hf_energy": -1691.1219513602027,
    "expanded_nuc_repulsion_energy": 4508.097375290685,
    "expanded_xc_energy": -248.07425975424025,
    "homo": -0.16594063123683211,
    "lumo": -0.097217380409994,
    "method": "RestrictedKSDFT",
    "mp2_tflops": 0.0,
    "mp2_time": 6.95335580495915e-310,
    "n_atoms": 68,
    "nmers": [
      [
        {
          "fragments": [
            0
          ],
          "hf_energy": -1691.1219513602027,
          "num_basis_fns": 1508,
          "num_iters": 17,
          "schema_version": "0.2.0"
        }
      ]
    ],
    "num_iters": 17,
    "ri_fock_time": 4.081612905,
    "ri_tflops": 0.14033007566845684,
    "scf_tflops": 0.045219062696028274,
    "scf_time": 35.916251935,
    "schema_version": "0.2.0",
    "tflops": 0.4517251916420265,
    "total_time": 36.149006,
    "transforms_time": 0.546373086,
    "xc_tflops": 0.0,
    "xc_time": 21.680797586999997
  },
  "schema_version": "0.2.0"
}
