{
  "calculation_time": 24.948467412,
  "qmmbe": {
    "b_formation_time": 1.758627995,
    "b_tflops": 6.569891607576734,
    "diag_time": 3.587353701,
    "expanded_elec_energy": -5359.242984993242,
    "expanded_hf_energy": -1536.4023461152808,
    "expanded_nuc_repulsion_energy": 4047.636294468917,
    "expanded_xc_energy": -224.79565559095573,
    "homo": -0.17586178487499965,
    "lumo": -0.10811931136985416,
    "method": "RestrictedKSDFT",
    "mp2_tflops": 0.0,
    "mp2_time": 6.95335580495915e-310,
    "n_atoms": 60,
    "nmers": [
      [
        {
          "fragments": [
            0
          ],
          "hf_energy": -1536.4023461152808,
          "num_basis_fns": 1360,
          "num_iters": 18,
          "schema_version": "0.2.0"
        }
      ]
    ],
    "num_iters": 18,
    "ri_fock_time": 0.20854229900000001,
    "ri_tflops": 2.1328613433958545,
    "scf_tflops": 36.60995763405663,
    "scf_time": 24.756512002,
    "schema_version": "0.2.0",
    "tflops": 33.86790185449498,
    "total_time": 24.943905,
    "transforms_time": 0.09197359799999998,
    "xc_tflops": 46.57652050294788,
    "xc_time": 17.865915003999994
  },
  "schema_version": "0.2.0"
}
