{
  "calculation_time": 34.424004486,
  "qmmbe": {
    "b_formation_time": 2.086326261,
    "b_tflops": 6.730559452877443,
    "diag_time": 4.756488061000001,
    "expanded_elec_energy": -5812.641802941022,
    "expanded_hf_energy": -1691.208543984365,
    "expanded_nuc_repulsion_energy": 4369.420297245774,
    "expanded_xc_energy": -247.98703828911687,
    "homo": -0.16467208238966854,
    "lumo": -0.11912485145542705,
    "method": "RestrictedKSDFT",
    "mp2_tflops": 0.0,
    "mp2_time": 6.95335580496547e-310,
    "n_atoms": 68,
    "nmers": [
      [
        {
          "fragments": [
            0
          ],
          "hf_energy": -1691.208543984365,
          "num_basis_fns": 1508,
          "num_iters": 18,
          "schema_version": "0.2.0"
        }
      ]
    ],
    "num_iters": 18,
    "ri_fock_time": 0.290537416,
    "ri_tflops": 2.0873923516687434,
    "scf_tflops": 36.46169372317005,
    "scf_time": 34.239536212,
    "schema_version": "0.2.0",
    "tflops": 34.205113106829565,
    "total_time": 34.41951,
    "transforms_time": 0.09811315800000002,
    "xc_tflops": 45.58960941683184,
    "xc_time": 25.482559269
  },
  "schema_version": "0.2.0"
}
