{
  "calculation_time": 32.924258138,
  "qmmbe": {
    "b_formation_time": 2.230479962,
    "b_tflops": 7.166264540969681,
    "diag_time": 4.514491346000001,
    "expanded_elec_energy": -6120.140694450869,
    "expanded_hf_energy": -1691.2020230036198,
    "expanded_nuc_repulsion_energy": 4676.940020474081,
    "expanded_xc_energy": -248.00134902683223,
    "homo": -0.17645451774724694,
    "lumo": -0.10339458676518123,
    "method": "RestrictedKSDFT",
    "mp2_tflops": 0.0,
    "mp2_time": 6.95335580496547e-310,
    "n_atoms": 68,
    "nmers": [
      [
        {
          "fragments": [
            0
          ],
          "hf_energy": -1691.2020230036198,
          "num_basis_fns": 1508,
          "num_iters": 17,
          "schema_version": "0.2.0"
        }
      ]
    ],
    "num_iters": 17,
    "ri_fock_time": 0.274383111,
    "ri_tflops": 2.0874938173873243,
    "scf_tflops": 36.33171796254541,
    "scf_time": 32.720435815,
    "schema_version": "0.2.0",
    "tflops": 33.83670394882445,
    "total_time": 32.919644,
    "transforms_time": 0.09485991000000003,
    "xc_tflops": 45.44032274186997,
    "xc_time": 24.129227651
  },
  "schema_version": "0.2.0"
}
