{
  "calculation_time": 20.957547506,
  "qmmbe": {
    "b_formation_time": 1.632432629,
    "b_tflops": 5.754044287439933,
    "diag_time": 2.931903596,
    "expanded_elec_energy": -4907.796814771937,
    "expanded_hf_energy": -1460.090948558775,
    "expanded_nuc_repulsion_energy": 3661.5235936948397,
    "expanded_xc_energy": -213.81772748167796,
    "homo": -0.17433429704080444,
    "lumo": -0.10358022049151491,
    "method": "RestrictedKSDFT",
    "mp2_tflops": 0.0,
    "mp2_time": 6.953355804986e-310,
    "n_atoms": 58,
    "nmers": [
      [
        {
          "fragments": [
            0
          ],
          "hf_energy": -1460.090948558775,
          "num_basis_fns": 1298,
          "num_iters": 16,
          "schema_version": "0.2.0"
        }
      ]
    ],
    "num_iters": 16,
    "ri_fock_time": 0.170193015,
    "ri_tflops": 2.0197887071217346,
    "scf_tflops": 34.652067631360836,
    "scf_time": 20.798169653,
    "schema_version": "0.2.0",
    "tflops": 31.771731894479377,
    "total_time": 20.953618,
    "transforms_time": 0.076242028,
    "xc_tflops": 43.91820259734175,
    "xc_time": 14.928570246000001
  },
  "schema_version": "0.2.0"
}
