{
  "calculation_time": 31.441467984,
  "qmmbe": {
    "b_formation_time": 2.145153072,
    "b_tflops": 6.797309319516943,
    "diag_time": 4.2740248780000005,
    "expanded_elec_energy": -5909.340739327383,
    "expanded_hf_energy": -1691.12360730037,
    "expanded_nuc_repulsion_energy": 4466.088864686073,
    "expanded_xc_energy": -247.8717326590601,
    "homo": -0.17828778256438435,
    "lumo": -0.10174722362156817,
    "method": "RestrictedKSDFT",
    "mp2_tflops": 0.0,
    "mp2_time": 6.95335580496705e-310,
    "n_atoms": 68,
    "nmers": [
      [
        {
          "fragments": [
            0
          ],
          "hf_energy": -1691.12360730037,
          "num_basis_fns": 1508,
          "num_iters": 16,
          "schema_version": "0.2.0"
        }
      ]
    ],
    "num_iters": 16,
    "ri_fock_time": 0.257996911,
    "ri_tflops": 2.0894843798498037,
    "scf_tflops": 36.03029628396968,
    "scf_time": 31.253830584,
    "schema_version": "0.2.0",
    "tflops": 33.527068127213916,
    "total_time": 31.437055,
    "transforms_time": 0.08811837199999999,
    "xc_tflops": 45.10402156861331,
    "xc_time": 23.014086297
  },
  "schema_version": "0.2.0"
}
