{
  "calculation_time": 31.776064894,
  "qmmbe": {
    "b_formation_time": 2.192766284,
    "b_tflops": 6.432566971738424,
    "diag_time": 4.3078155030000005,
    "expanded_elec_energy": -5853.721742673317,
    "expanded_hf_energy": -1691.1292255603041,
    "expanded_nuc_repulsion_energy": 4410.455024260983,
    "expanded_xc_energy": -247.8625071479703,
    "homo": -0.17262397051633904,
    "lumo": -0.1073408003869566,
    "method": "RestrictedKSDFT",
    "mp2_tflops": 0.0,
    "mp2_time": 6.95335580496547e-310,
    "n_atoms": 68,
    "nmers": [
      [
        {
          "fragments": [
            0
          ],
          "hf_energy": -1691.1292255603041,
          "num_basis_fns": 1508,
          "num_iters": 16,
          "schema_version": "0.2.0"
        }
      ]
    ],
    "num_iters": 16,
    "ri_fock_time": 0.25817459800000003,
    "ri_tflops": 2.088046305717497,
    "scf_tflops": 35.664499483894446,
    "scf_time": 31.594719806,
    "schema_version": "0.2.0",
    "tflops": 33.172386176816545,
    "total_time": 31.771493,
    "transforms_time": 0.08634467600000002,
    "xc_tflops": 44.46107800512331,
    "xc_time": 23.356671737
  },
  "schema_version": "0.2.0"
}
