{
  "calculation_time": 12.291646705,
  "qmmbe": {
    "b_formation_time": 1.035684562,
    "b_tflops": 3.384939862552475,
    "diag_time": 1.9966870260000005,
    "expanded_elec_energy": -3248.3109513080562,
    "expanded_hf_energy": -1076.5681666484452,
    "expanded_nuc_repulsion_energy": 2329.723745506012,
    "expanded_xc_energy": -157.98096084640122,
    "homo": -0.1588604996050378,
    "lumo": -0.11644391621172331,
    "method": "RestrictedKSDFT",
    "mp2_tflops": 0.0,
    "mp2_time": 6.953355804986e-310,
    "n_atoms": 44,
    "nmers": [
      [
        {
          "fragments": [
            0
          ],
          "hf_energy": -1076.5681666484452,
          "num_basis_fns": 964,
          "num_iters": 17,
          "schema_version": "0.2.0"
        }
      ]
    ],
    "num_iters": 17,
    "ri_fock_time": 0.078596568,
    "ri_tflops": 1.9038866824821155,
    "scf_tflops": 26.4638800901399,
    "scf_time": 12.187015287,
    "schema_version": "0.2.0",
    "tflops": 24.00350175933259,
    "total_time": 12.28861,
    "transforms_time": 0.06005395100000001,
    "xc_tflops": 33.77729191745544,
    "xc_time": 8.618469369
  },
  "schema_version": "0.2.0"
}
