{
  "calculation_time": 31.548060847,
  "qmmbe": {
    "b_formation_time": 2.260971664,
    "b_tflops": 7.291223547746329,
    "diag_time": 4.238225642,
    "expanded_elec_energy": -6188.254565019817,
    "expanded_hf_energy": -1691.0946064788736,
    "expanded_nuc_repulsion_energy": 4745.044267557483,
    "expanded_xc_energy": -247.88430901653965,
    "homo": -0.17957537742834445,
    "lumo": -0.09447046473545964,
    "method": "RestrictedKSDFT",
    "mp2_tflops": 0.0,
    "mp2_time": 6.95335580496705e-310,
    "n_atoms": 68,
    "nmers": [
      [
        {
          "fragments": [
            0
          ],
          "hf_energy": -1691.0946064788736,
          "num_basis_fns": 1508,
          "num_iters": 16,
          "schema_version": "0.2.0"
        }
      ]
    ],
    "num_iters": 16,
    "ri_fock_time": 0.257578806,
    "ri_tflops": 2.092876055897239,
    "scf_tflops": 35.918823226159525,
    "scf_time": 31.322769875,
    "schema_version": "0.2.0",
    "tflops": 33.30039776196204,
    "total_time": 31.543485,
    "transforms_time": 0.08926885000000002,
    "xc_tflops": 44.753462601699525,
    "xc_time": 23.071938611000004
  },
  "schema_version": "0.2.0"
}
